iaptoolkit/__init__.py
iaptoolkit/constants.py
iaptoolkit/exceptions.py
iaptoolkit/headers.py
iaptoolkit/tokens/__init__.py
iaptoolkit/tokens/service_account.py
iaptoolkit/tokens/structs.py
iaptoolkit/tokens/token_datastore.py
iaptoolkit/utils/__init__.py
iaptoolkit/utils/urls.py
iaptoolkit/utils/verify.py
iaptoolkit-0.4.0.dist-info/METADATA
iaptoolkit-0.4.0.dist-info/WHEEL
iaptoolkit-0.4.0.dist-info/licenses/LICENSE
iaptoolkit-0.4.0.dist-info/RECORD
