Metadata-Version: 2.4
Name: iaptoolkit
Version: 0.4.0
Summary: Library of common utils for interacting with Identity-Aware Proxies
License-File: LICENSE
Author: Rob Voigt
Author-email: code@ravoigt.com
Requires-Python: >=3.11,<4.0
Classifier: Programming Language :: Python :: 3
Classifier: Programming Language :: Python :: 3.11
Classifier: Programming Language :: Python :: 3.12
Classifier: Programming Language :: Python :: 3.13
Classifier: Programming Language :: Python :: 3.14
Requires-Dist: google-auth (>=2.29.0,<3.0.0)
Requires-Dist: google-cloud-iam (>=2.20.0,<3.0.0)
Requires-Dist: kvcommon[k8s] (>=0.4.5,<0.5.0)
Requires-Dist: requests (>=2.32.4)
Requires-Dist: toml (>=0.10.2,<0.11.0)
Project-URL: Homepage, https://github.com/RAVoigt/iaptoolkit
Project-URL: Repository, https://github.com/RAVoigt/iaptoolkit
